{"trial_id": "0512994d30db960a04729bff7a001ab8", "hyperparameters": {"space": [{"class_name": "Choice", "config": {"name": "activation", "default": "relu", "conditions": [], "values": ["relu", "tanh", "sigmoid"], "ordered": false}}, {"class_name": "Int", "config": {"name": "first_units", "default": null, "conditions": [], "min_value": 1, "max_value": 30, "step": 5, "sampling": null}}, {"class_name": "Int", "config": {"name": "num_layers", "default": null, "conditions": [], "min_value": 1, "max_value": 5, "step": 1, "sampling": null}}, {"class_name": "Int", "config": {"name": "units_0", "default": null, "conditions": [], "min_value": 1, "max_value": 30, "step": 5, "sampling": null}}, {"class_name": "Int", "config": {"name": "units_1", "default": null, "conditions": [], "min_value": 1, "max_value": 30, "step": 5, "sampling": null}}, {"class_name": "Int", "config": {"name": "units_2", "default": null, "conditions": [], "min_value": 1, "max_value": 30, "step": 5, "sampling": null}}, {"class_name": "Int", "config": {"name": "units_3", "default": null, "conditions": [], "min_value": 1, "max_value": 30, "step": 5, "sampling": null}}, {"class_name": "Int", "config": {"name": "units_4", "default": null, "conditions": [], "min_value": 1, "max_value": 30, "step": 5, "sampling": null}}], "values": {"activation": "tanh", "first_units": 21, "num_layers": 4, "units_0": 1, "units_1": 21, "units_2": 21, "units_3": 11, "units_4": 21, "tuner/epochs": 20, "tuner/initial_epoch": 5, "tuner/bracket": 2, "tuner/round": 2, "tuner/trial_id": "c850432c974d393e85a7c414d1febeff"}}, "metrics": {"metrics": {"loss": {"direction": "min", "observations": [{"value": [0.5446397662162781], "step": 0}]}, "accuracy": {"direction": "max", "observations": [{"value": [0.8021364212036133], "step": 0}]}, "val_loss": {"direction": "min", "observations": [{"value": [0.45654845237731934], "step": 0}]}, "val_accuracy": {"direction": "max", "observations": [{"value": [0.8186349868774414], "step": 0}]}}}, "score": 0.8186349868774414, "best_step": 0, "status": "COMPLETED"}